daq/__init__.py
daq/kartothek.py
daq/stats.py
daq/synapse.py
daq-0.4.1.dist-info/LICENSE
daq-0.4.1.dist-info/METADATA
daq-0.4.1.dist-info/WHEEL
daq-0.4.1.dist-info/entry_points.txt
daq-0.4.1.dist-info/top_level.txt
daq-0.4.1.dist-info/RECORD
