Metadata-Version: 2.1
Name: daq
Version: 0.4.1
Summary: Dataset Query
Home-page: UNKNOWN
Author: Peter Hoffmann
Author-email: UNKNOWN
License: UNKNOWN
Platform: UNKNOWN
Classifier: Programming Language :: Python
